ipysketch_lite/__init__.py
ipysketch_lite/_template.py
ipysketch_lite/_legacy/__init__.py
ipysketch_lite-0.4.2.dist-info/LICENSE
ipysketch_lite-0.4.2.dist-info/METADATA
ipysketch_lite-0.4.2.dist-info/WHEEL
ipysketch_lite-0.4.2.dist-info/top_level.txt
ipysketch_lite-0.4.2.dist-info/RECORD
