Metadata-Version: 2.2
Name: ipysketch-lite
Version: 0.4.2
Summary: Simple sketching tool for Jupyter notebooks
Author-email: Matthew Taylor <matthew.taylor.andre@gmail.com>
License: Copyright (c) 2025 Matthew Andre Taylor
Project-URL: Homepage, https://github.com/MatthewAndreTaylor/ipysketch_lite
Keywords: jupyter,sketch,drawing,canvas
Classifier: Framework :: Jupyter
Classifier: Framework :: Jupyter :: JupyterLab
Classifier: Framework :: Jupyter :: JupyterLab :: 4
Classifier: Framework :: Jupyter :: JupyterLab :: Extensions
Classifier: Framework :: Jupyter :: JupyterLab :: Extensions :: Prebuilt
Classifier: License :: OSI Approved :: BSD License
Classifier: Programming Language :: Python
Classifier: Programming Language :: Python :: 3
Classifier: Programming Language :: Python :: 3.9
Classifier: Programming Language :: Python :: 3.10
Classifier: Programming Language :: Python :: 3.11
Classifier: Programming Language :: Python :: 3.12
Requires-Python: >=3.9
License-File: LICENSE
Requires-Dist: pillow==10.2.0
Requires-Dist: anywidget
Requires-Dist: ipywidgets==8.1.2
